cmem_plugin_llm/__init__.py
cmem_plugin_llm/commons.py
cmem_plugin_llm/create_embedding.py
cmem_plugin_llm/create_embedding.svg
cmem_plugin_llm/execute_instruction.py
cmem_plugin_llm/execute_instruction.svg
cmem_plugin_llm-2.1.0.dist-info/METADATA
cmem_plugin_llm-2.1.0.dist-info/WHEEL
cmem_plugin_llm-2.1.0.dist-info/licenses/LICENSE
cmem_plugin_llm-2.1.0.dist-info/RECORD
