Metadata-Version: 2.4
Name: cmem-plugin-llm
Version: 2.1.0
Summary: Interact with Large Language Models (Execute Instructions, Create Embeddings).
License: Apache-2.0
License-File: LICENSE
Keywords: eccenca Corporate Memory,plugin
Author: eccenca GmbH
Author-email: cmempy-developer@eccenca.com
Requires-Python: >=3.13,<4.0
Classifier: Development Status :: 4 - Beta
Classifier: Environment :: Plugins
Classifier: License :: OSI Approved :: Apache Software License
Classifier: Programming Language :: Python :: 3
Classifier: Programming Language :: Python :: 3.13
Classifier: Programming Language :: Python :: 3.14
Requires-Dist: cmem-plugin-base (>=4.15.0,<5.0.0)
Requires-Dist: jinja2 (>=3.1.6,<4.0.0)
Requires-Dist: openai (>=1.99.9,<2.0.0)
Requires-Dist: pydantic (>=2.11.9,<3.0.0)
